<?xml version="1.0" encoding="utf-8"?>
<!DOCTYPE hibernate-mapping PUBLIC "-//Hibernate/Hibernate Mapping DTD 3.0//EN"
        "http://hibernate.sourceforge.net/hibernate-mapping-3.0.dtd">
<hibernate-mapping>
    <class name="com.cndym.entity.data.pick.FillPickReg" table="USER_FILL_PICK_REGISTERED">
        <id name="id" column="ID">
            <generator class="sequence">
                <param name="sequence">SEQ_FILL_PICK_REG</param>
            </generator>
        </id>
        <property name="userCode" column="USER_CODE" type="java.lang.String" />
        <property name="orderId" column="ORDER_ID" type="java.lang.String" />
        <property name="outOrderId" column="OUT_ORDER_ID" type="java.lang.String" />
        <property name="fillResources" column="FILL_RESOURCES" type="java.lang.String" />
        <property name="amount" column="AMOUNT" type="java.lang.Double" />
        <property name="realAmount" column="REAL_AMOUNT" type="java.lang.Double" />
        <property name="createTime" column="CREATE_TIME" type="java.util.Date" />
        <property name="acceptTime" column="ACCEPT_TIME" type="java.util.Date" />
        <property name="status" column="STATUS" type="java.lang.Integer" />
        <property name="sid" column="SID" type="java.lang.String" />
        <property name="platform" column="PLAT_FORM" type="java.lang.String" />
        <property name="softVer" column="SOFT_VER" type="java.lang.String" />
    </class>
</hibernate-mapping>